README.md
setup.py
hwinfo/__init__.py
hwinfo/hwinfo.py
hwinfo.egg-info/PKG-INFO
hwinfo.egg-info/SOURCES.txt
hwinfo.egg-info/dependency_links.txt
hwinfo.egg-info/top_level.txt